django_dto/__init__.py
django_dto/core.py
django_dto/dto.py
django_dto/exceptions.py
django_dto-0.1.4.dist-info/LICENSE
django_dto-0.1.4.dist-info/METADATA
django_dto-0.1.4.dist-info/WHEEL
django_dto-0.1.4.dist-info/RECORD
